redpepper/requests/__init__.py
redpepper/requests/data.py
redpepper/requests/dataFileContents.py
redpepper/requests/dataFileHash.py
redpepper/requests/dataFileStat.py
redpepper/requests/noop.py
redpepper/requests/operationModule.py
redpepper/requests/stateDefinition.py
redpepper_requests-0.3.3.dist-info/METADATA
redpepper_requests-0.3.3.dist-info/WHEEL
redpepper_requests-0.3.3.dist-info/RECORD
